{"cameraMode":{"drawMode":0,"name":"Shaded","section":"Shading Mode"},"sceneLighting":true,"audioPlay":false,"sceneViewState":{"showFog":true,"showMaterialUpdate":false,"showSkybox":true,"showFlares":true,"showImageEffects":true,"showParticleSystems":true},"in2DMode":false,"pivot":{"x":9.240954399108887,"y":28.95136070251465,"z":-28.55478286743164},"rotation":{"x":0.01475664135068655,"y":0.9405954480171204,"z":-0.33676013350486758,"w":0.04122736304998398},"size":7.781307220458984,"orthographic":false}